[
  {
    "customer_id": "CUST1001",
    "customer_name": "Rahul Sharma",
    "email": "rahul.sharma@example.com",
    "phone": "9876543210",
    "city": "Pune",
    "registration_date": "2026-04-20",
    "orders": [
      {
        "order_id": "ORD5001",
        "order_date": "2026-04-21",
        "product_name": "Laptop",
        "quantity": 1,
        "price": 55000
      },
      {
        "order_id": "ORD5002",
        "order_date": "2026-04-22",
        "product_name": "Mouse",
        "quantity": 2,
        "price": 800
      }
    ]
  },
  {
    "customer_id": "CUST1002",
    "customer_name": "Priya Patil",
    "email": "priya.patil@example.com",
    "phone": "9123456780",
    "city": "Mumbai",
    "registration_date": "2026-04-19",
    "orders": [
      {
        "order_id": "ORD5003",
        "order_date": "2026-04-22",
        "product_name": "Mobile Phone",
        "quantity": 1,
        "price": 25000
      }
    ]
  },
  {
    "customer_id": "CUST1003",
    "customer_name": "Amit Joshi",
    "email": "amit.joshi@example.com",
    "phone": "9988776655",
    "city": "Solapur",
    "registration_date": "2026-04-18",
    "orders": []
  }
]